mbeacon/__init__.py
mbeacon/ip.py
mbeacon/mbeacon.py
mbeacon/transport.py
mbeacon-0.0.1.dist-info/LICENSE
mbeacon-0.0.1.dist-info/METADATA
mbeacon-0.0.1.dist-info/WHEEL
mbeacon-0.0.1.dist-info/top_level.txt
mbeacon-0.0.1.dist-info/RECORD
