Metadata-Version: 2.1
Name: mbeacon
Version: 0.0.1
Summary: A multicast framework and tools
Home-page: https://github.com/MomsFriendlyRobotCompany/mbeacon
Author: Kevin Walchko
Author-email: walchko@noreply.github.com
License: MIT
Keywords: multicast
Platform: UNKNOWN
Classifier: Development Status :: 4 - Beta
Classifier: License :: OSI Approved :: MIT License
Classifier: Programming Language :: Python :: 3.7
Classifier: Operating System :: Unix
Classifier: Operating System :: POSIX :: Linux
Classifier: Operating System :: MacOS :: MacOS X
Classifier: Operating System :: POSIX
Classifier: Topic :: Scientific/Engineering
Classifier: Topic :: Scientific/Engineering :: Artificial Intelligence
Classifier: Topic :: Scientific/Engineering :: Image Recognition
Classifier: Topic :: Software Development :: Libraries :: Python Modules
Requires-Dist: build-utils
